MANIFEST.in
README.md
setup.cfg
setup.py
http_reqtrace/__init__.py
http_reqtrace/__main__.py
http_reqtrace/app.py
http_reqtrace.egg-info/PKG-INFO
http_reqtrace.egg-info/SOURCES.txt
http_reqtrace.egg-info/dependency_links.txt
http_reqtrace.egg-info/requires.txt
http_reqtrace.egg-info/top_level.txt